MANIFEST.in
setup.py
getchs/__init__.py
iterm2_color_scheme/__init__.py
iterm2_color_scheme/iterm2_color_scheme.py
iterm2_color_scheme/version.txt
iterm2_color_scheme.egg-info/PKG-INFO
iterm2_color_scheme.egg-info/SOURCES.txt
iterm2_color_scheme.egg-info/dependency_links.txt
iterm2_color_scheme.egg-info/entry_points.txt
iterm2_color_scheme.egg-info/not-zip-safe
iterm2_color_scheme.egg-info/top_level.txt
iterm2_color_scheme/iTerm2-Color-Schemes/.git
iterm2_color_scheme/iTerm2-Color-Schemes/.gitignore
iterm2_color_scheme/iTerm2-Color-Schemes/README.md
iterm2_color_scheme/iTerm2-Color-Schemes/schemes/3024 Day.itermcolors
iterm2_color_scheme/iTerm2-Color-Schemes/schemes/3024 Night.itermcolors
iterm2_color_scheme/iTerm2-Color-Schemes/schemes/AdventureTime.itermcolors
iterm2_color_scheme/iTerm2-Color-Schemes/schemes/Afterglow.itermcolors
iterm2_color_scheme/iTerm2-Color-Schemes/schemes/AlienBlood.itermcolors
iterm2_color_scheme/iTerm2-Color-Schemes/schemes/Argonaut.itermcolors
iterm2_color_scheme/iTerm2-Color-Schemes/schemes/Arthur.itermcolors
iterm2_color_scheme/iTerm2-Color-Schemes/schemes/AtelierSulphurpool.itermcolors
iterm2_color_scheme/iTerm2-Color-Schemes/schemes/Atom.itermcolors
iterm2_color_scheme/iTerm2-Color-Schemes/schemes/AtomOneLight.itermcolors
iterm2_color_scheme/iTerm2-Color-Schemes/schemes/Batman.itermcolors
iterm2_color_scheme/iTerm2-Color-Schemes/schemes/Belafonte Day.itermcolors
iterm2_color_scheme/iTerm2-Color-Schemes/schemes/Belafonte Night.itermcolors
iterm2_color_scheme/iTerm2-Color-Schemes/schemes/BirdsOfParadise.itermcolors
iterm2_color_scheme/iTerm2-Color-Schemes/schemes/Blazer.itermcolors
iterm2_color_scheme/iTerm2-Color-Schemes/schemes/Borland.itermcolors
iterm2_color_scheme/iTerm2-Color-Schemes/schemes/Bright Lights.itermcolors
iterm2_color_scheme/iTerm2-Color-Schemes/schemes/Broadcast.itermcolors
iterm2_color_scheme/iTerm2-Color-Schemes/schemes/Brogrammer.itermcolors
iterm2_color_scheme/iTerm2-Color-Schemes/schemes/C64.itermcolors
iterm2_color_scheme/iTerm2-Color-Schemes/schemes/CLRS.itermcolors
iterm2_color_scheme/iTerm2-Color-Schemes/schemes/Chalk.itermcolors
iterm2_color_scheme/iTerm2-Color-Schemes/schemes/Chalkboard.itermcolors
